modularapp/__init__.py
modularapp/application.py
modularapp/application_module.py
modularapp/dependency_provider.py
modularapp/transaction_context.py
modularapp/utils.py
modularapp-0.1.0.dist-info/LICENSE
modularapp-0.1.0.dist-info/METADATA
modularapp-0.1.0.dist-info/WHEEL
modularapp-0.1.0.dist-info/RECORD
