Metadata-Version: 2.1
Name: modularapp
Version: 0.1.0
Summary: 
Author: Przemysław Górecki
Author-email: przemyslaw.gorecki@gmail.com
Requires-Python: >=3.10,<4.0
Classifier: Programming Language :: Python :: 3
Classifier: Programming Language :: Python :: 3.10
Classifier: Programming Language :: Python :: 3.11
Requires-Dist: pytest (>=7.4.2,<8.0.0)
